kafka_store/__init__.py
kafka_store/buffer.py
kafka_store/handler.py
kafka_store/kafka_store.py
kafka_store/read.py
kafka_store/store.py
kafka_store-0.1.4.data/scripts/kafka-store
kafka_store-0.1.4.data/scripts/kafka-store-reader
kafka_store-0.1.4.dist-info/DESCRIPTION.rst
kafka_store-0.1.4.dist-info/METADATA
kafka_store-0.1.4.dist-info/RECORD
kafka_store-0.1.4.dist-info/WHEEL
kafka_store-0.1.4.dist-info/metadata.json
kafka_store-0.1.4.dist-info/top_level.txt
