Metadata-Version: 2.0
Name: kafka-store
Version: 0.1.4
Summary: Kafka Store provides an easy way of archiving data from Kafka
Home-page: https://github.com/smyte/kafka_store
Author: Josh Yudaken
Author-email: josh@smyte.com
License: Apache Software License 2.0
Keywords: kafka_store
Platform: UNKNOWN
Classifier: Development Status :: 2 - Pre-Alpha
Classifier: Intended Audience :: Developers
Classifier: License :: OSI Approved :: Apache Software License
Classifier: Natural Language :: English
Classifier: Programming Language :: Python :: 3
Classifier: Programming Language :: Python :: 3.3
Classifier: Programming Language :: Python :: 3.4
Classifier: Programming Language :: Python :: 3.5
Requires-Dist: bitmath
Requires-Dist: confluent-kafka-smyte
Requires-Dist: docopt
Requires-Dist: fastavro
Requires-Dist: google-api-python-client
Requires-Dist: mock
Requires-Dist: mysqlclient
Requires-Dist: smyte-pylib
